loggz/__init__.py
loggz/formatters.py
loggz-0.1.0.dist-info/LICENSE
loggz-0.1.0.dist-info/METADATA
loggz-0.1.0.dist-info/WHEEL
loggz-0.1.0.dist-info/top_level.txt
loggz-0.1.0.dist-info/RECORD
