Metadata-Version: 2.1
Name: loggz
Version: 0.1.0
Summary: A helper to implement simple but standard and jsonified strategies for logging.
Home-page: http://pypi.python.org/pypi/loggz/
Author: Deepnox
Author-email: opensource@deepnox.io
License: MIT
Platform: UNKNOWN
Classifier: Development Status :: 3 - Alpha
Classifier: Programming Language :: Python :: 3
Classifier: Programming Language :: Python :: 3.7
Classifier: Topic :: System :: Logging
